trusted_publishing_examples/__init__.py
trusted_publishing_examples/py.typed
trusted_publishing_examples-0.1.3.dist-info/METADATA
trusted_publishing_examples-0.1.3.dist-info/WHEEL
trusted_publishing_examples-0.1.3.dist-info/RECORD
