Metadata-Version: 2.4
Name: trusted-publishing-examples
Version: 0.1.3
Summary: Add your description here
Author-email: konstin <konstin@mailbox.org>
Requires-Python: >=3.13
Requires-Dist: numpy>=2.1.2
